dedup/__init__.py
dedup/cmd.py
dedup/dedup_utils.py
dedup/image_utils.py
dedup/webapp.py
dedup/templates/index.html
dedup_img-1.0.2.dist-info/METADATA
dedup_img-1.0.2.dist-info/WHEEL
dedup_img-1.0.2.dist-info/entry_points.txt
dedup_img-1.0.2.dist-info/top_level.txt
dedup_img-1.0.2.dist-info/RECORD
