Metadata-Version: 2.1
Name: dedup-img
Version: 1.0.2
Summary: imagededup图片查重封装使用
Home-page: https://cjlmonster.cn/python/dedupimg/
Author: cjlmonster
Author-email: cjlmonster@163.com
License: UNKNOWN
Platform: python3
Requires-Python: >=3
Requires-Dist: imagededup (>=0.2.2)
Requires-Dist: flask (>=2.0.1)
